anomalytracker/__init__.py
anomalytracker/admin.py
anomalytracker/app_settings.py
anomalytracker/apps.py
anomalytracker/auth_hooks.py
anomalytracker/forms.py
anomalytracker/models.py
anomalytracker/tasks.py
anomalytracker/urls.py
anomalytracker/utils.py
anomalytracker/views.py
anomalytracker/locale/.gitkeep
anomalytracker/management/__init__.py
anomalytracker/management/commands/__init__.py
anomalytracker/management/commands/clean_permissions.py
anomalytracker/migrations/0001_initial.py
anomalytracker/migrations/0002_default_config.py
anomalytracker/migrations/0003_remove_anomalies_unique_anom_per_system.py
anomalytracker/migrations/__init__.py
anomalytracker/static/example/.gitkeep
anomalytracker/templates/anomalytracker/anomaly_form.html
anomalytracker/templates/anomalytracker/base.html
anomalytracker/templates/anomalytracker/index.html
anomalytracker/templates/anomalytracker/manageanoms.html
anomalytracker/tests/__init__.py
anomalytracker/tests/test_example.py
aa_anomaly_tracker-0.1.2.dist-info/METADATA
aa_anomaly_tracker-0.1.2.dist-info/WHEEL
aa_anomaly_tracker-0.1.2.dist-info/licenses/LICENSE
aa_anomaly_tracker-0.1.2.dist-info/RECORD
